README.md
setup.py
vizbee/__init__.py
vizbee/app.py
vizbee/cli.py
vizbee/scheduler.py
vizbee/schema.py
vizbee.egg-info/PKG-INFO
vizbee.egg-info/SOURCES.txt
vizbee.egg-info/dependency_links.txt
vizbee.egg-info/entry_points.txt
vizbee.egg-info/requires.txt
vizbee.egg-info/top_level.txt