Metadata-Version: 1.0
Name: vizbee
Version: 0.1b0
Summary: vizbee.io agent
Home-page: https://github.com/jeanphix/kpid
Author: jean-philippe serafin
Author-email: serafinjp@gmail.com
License: MIT
Platform: UNKNOWN
